{"sections":{"main":{"type":"main-page","disabled":true,"settings":{"show_page_title":false,"disable_top_spacing":false,"disable_bottom_spacing":false}},"slideshow_hM9xbj":{"type":"slideshow","blocks":{"slide_wQU4yT":{"type":"slide","name":"Masthead","settings":{"image":"shopify:\/\/shop_images\/JP_Home_Lifestyle_Page_BG_Image.png","mobile_image":"shopify:\/\/shop_images\/JP_Home_Lifestyle_Page-13.png","slide_link":"","video_background":false,"video":"","subheading":"","heading":"","heading_size":"h1-xlarge","content":"","description_size":"medium","content_position":"middle-center","text_alignment":"center","content_size":"medium","overlay_color":"#ffffff","overlay_opacity":0,"overlay_gradient":"","button_1_text":"","button_1_link":"","button_1_outline":true,"button_2_text":"","button_2_link":"","button_2_outline":false}}},"block_order":["slide_wQU4yT"],"name":"Home mastead","settings":{"desktop_height":"desktop-height-image","mobile_height":"mobile-height-full","full_width":true,"autoplay":true,"autoplay_length":5,"transition":"swipe","disable_top_spacing":true,"disable_bottom_spacing":true}},"spacer_hckc3N":{"type":"spacer","disabled":true,"name":"Spacer","settings":{"spacer_mobile":65,"spacer_desktop":50,"border_separator":false,"border_separator_full":false}},"rich_text_X8RFyy":{"type":"rich-text","blocks":{"text_q3MU4n":{"type":"text","settings":{"text":"<p>When your home is truly a sanctuary, embrace a refined simplicity with Jaspal Home's latest collection.<\/p>","custom_liquid":"","size":"text-size-small"}}},"block_order":["text_q3MU4n"],"name":"Rich text","settings":{"section_width":"full-width-row-full","text_width":"xlarge","text_position":"center","text_alignment":"center","color_bg":"rgba(0,0,0,0)","color_text":"#151515","color_links":"#151515","disable_top_spacing":false,"disable_bottom_spacing":true}},"rich_text_7hmYrg":{"type":"rich-text","blocks":{"heading_f6TG8V":{"type":"heading","settings":{"text":"Neutral Chic","size":"h4"}},"text_x3ja4w":{"type":"text","settings":{"text":"<p>Introduce a touch of warmth to your living room with a monogram cushion and a soft throw that echo the tranquility of nature. In the bathroom, elevate your experience with plush towels and a bath rug that invite relaxation. Envelop yourself in serenity with our selection of aromatic candles and reed diffusers, available in Serene Bloom and Silk Peony. And for the bedroom, experience effortless comfort with our loungewear, designed for ease.<\/p>","custom_liquid":"","size":"text-size-small"}}},"block_order":["heading_f6TG8V","text_x3ja4w"],"name":"Text: Contemporary Greek","settings":{"section_width":"full-width-row-full","text_width":"xlarge","text_position":"center","text_alignment":"center","color_bg":"rgba(0,0,0,0)","color_text":"#151515","color_links":"#151515","disable_top_spacing":true,"disable_bottom_spacing":true}},"multicolumn_PKXkUq":{"type":"multicolumn","blocks":{"column_JhPMNJ":{"type":"column","name":"HOME DECORATION","settings":{"image":"shopify:\/\/shop_images\/JP_Home_Lifestyle_Page-02.png","image_full_width":true,"image_link":"shopify:\/\/collections\/home-decoration","retina":true,"title":"","text":"","link_label":"HOME DECORATION","link":"shopify:\/\/collections\/home-decoration"}},"column_XQWyhJ":{"type":"column","name":"BEDDING & LINENS","settings":{"image":"shopify:\/\/shop_images\/JP_Home_Lifestyle_Page-03.png","image_full_width":true,"image_link":"shopify:\/\/collections\/bedding-linens","retina":true,"title":"","text":"","link_label":"BEDDING & LINENS","link":"shopify:\/\/collections\/bedding-linens"}},"column_WYXVyG":{"type":"column","name":"FRAGRANCES","settings":{"image":"shopify:\/\/shop_images\/JP_Home_Lifestyle_Page-04.png","image_full_width":true,"image_link":"shopify:\/\/collections\/fragrances","retina":true,"title":"","text":"","link_label":"FRAGRANCES","link":"shopify:\/\/collections\/fragrances"}}},"block_order":["column_JhPMNJ","column_XQWyhJ","column_WYXVyG"],"name":"3Block","settings":{"heading":"","heading_left":false,"description":"","full_width":true,"display_type":"grid","image_ratio":"adapt","columns_desktop":3,"text_alignment":"center","heading_size":"h5","mobile_swipe":true,"show_progress_bar":true,"disable_top_spacing":true,"disable_bottom_spacing":true}},"spacer_4NyKKa":{"type":"spacer","name":"Spacer","settings":{"spacer_mobile":65,"spacer_desktop":50,"border_separator":false,"border_separator_full":false}},"rich_text_i67AyK":{"type":"rich-text","blocks":{"heading_DDJ7Mw":{"type":"heading","settings":{"text":"LATEST","size":"h3"}}},"block_order":["heading_DDJ7Mw"],"name":"Text: Latest","settings":{"section_width":"full-width-row-full","text_width":"xlarge","text_position":"left","text_alignment":"left","color_bg":"rgba(0,0,0,0)","color_text":"#151515","color_links":"#151515","disable_top_spacing":false,"disable_bottom_spacing":true}},"collection_tabs_JyaJkc":{"type":"collection-tabs","blocks":{"collection_Yx7tK9":{"type":"collection","settings":{"collection":"home-lifestyle","enable_promotion":false,"title":"","text":"","link_label":"","content_position":"bottom-left","text_alignment":"left","link":"","use_text_button":false,"block_link":"","overlay_color":"#000000","overlay_opacity":0}}},"block_order":["collection_Yx7tK9"],"name":"Product Slide","settings":{"heading":"","heading_left":false,"description":"","full_width":true,"product_limit":16,"columns_desktop":4,"show_view_all":false,"show_progress_bar":false,"disable_top_spacing":true,"disable_bottom_spacing":false}},"spacer_CikTKW":{"type":"spacer","name":"Spacer","settings":{"spacer_mobile":25,"spacer_desktop":25,"border_separator":false,"border_separator_full":false}},"rich_text_WDD3eK":{"type":"rich-text","blocks":{"heading_Xygd7r":{"type":"heading","settings":{"text":"Contemporary Greek","size":"h4"}},"text_NTJRQj":{"type":"text","settings":{"text":"<p>This collection melds modern design with thoughtful materials, encouraging you to merge vibrant colors from the outside world into your living space. Let our reed diffusers fill your home with the uplifting scents of Celeste Breeze, Solea Horizon, and Ionia Wave, creating an ambiance that celebrates the outdoors.<\/p>","custom_liquid":"","size":"text-size-small"}}},"block_order":["heading_Xygd7r","text_NTJRQj"],"name":"Text: Contemporary Greek","settings":{"section_width":"full-width-row-full","text_width":"xlarge","text_position":"center","text_alignment":"center","color_bg":"rgba(0,0,0,0)","color_text":"#151515","color_links":"#151515","disable_top_spacing":true,"disable_bottom_spacing":true}},"single_image_N7FJj6":{"type":"single-image","custom_css":["img {width: 75%;}","@media only screen and (max-width: 600px) {img {width: 100%; margin: 0 auto; \/* Center the element *\/ }}"],"name":"LPT: Contemporary Greek","settings":{"image":"shopify:\/\/shop_images\/JP_Home_Lifestyle_Page_LPT_1.png","full_width":true,"disable_top_spacing":true,"disable_bottom_spacing":false}},"multicolumn_EzgfxQ":{"type":"multicolumn","blocks":{"column_6rQ6bi":{"type":"column","name":"1","settings":{"image":"shopify:\/\/shop_images\/JP_Home_Lifestyle_Page-05.png","image_full_width":true,"image_link":"","retina":true,"title":"","text":"","link_label":"","link":""}},"column_LAxnzn":{"type":"column","name":"2","settings":{"image":"shopify:\/\/shop_images\/JP_Home_Lifestyle_Page-06.png","image_full_width":true,"image_link":"","retina":true,"title":"","text":"","link_label":"","link":""}},"column_yELGxt":{"type":"column","name":"3","settings":{"image":"shopify:\/\/shop_images\/JP_Home_Lifestyle_Page-07.png","image_full_width":true,"image_link":"","retina":true,"title":"","text":"","link_label":"","link":""}}},"block_order":["column_6rQ6bi","column_LAxnzn","column_yELGxt"],"name":"3Block: Contemporary Greek","settings":{"heading":"","heading_left":true,"description":"","full_width":false,"display_type":"grid","image_ratio":"adapt","columns_desktop":3,"text_alignment":"left","heading_size":"h5","mobile_swipe":true,"show_progress_bar":true,"disable_top_spacing":true,"disable_bottom_spacing":true}},"spacer_tbiAh6":{"type":"spacer","disabled":true,"name":"Spacer","settings":{"spacer_mobile":25,"spacer_desktop":25,"border_separator":false,"border_separator_full":false}},"rich_text_zPA9gg":{"type":"rich-text","blocks":{"heading_NXViKm":{"type":"heading","settings":{"text":"Animal Capsule","size":"h4"}},"text_XzXAqV":{"type":"text","settings":{"text":"<p>Designed for your beloved companion, this collection seamlessly integrates into your lifestyle, whether at home, exploring the outdoors, or embarking on travels together.<\/p>","custom_liquid":"","size":"text-size-small"}}},"block_order":["heading_NXViKm","text_XzXAqV"],"name":"Text: Animal Capsule","settings":{"section_width":"full-width-row-full","text_width":"xlarge","text_position":"center","text_alignment":"center","color_bg":"rgba(0,0,0,0)","color_text":"#151515","color_links":"#151515","disable_top_spacing":false,"disable_bottom_spacing":true}},"single_image_QX9Htx":{"type":"single-image","custom_css":["img {width: 75%;}","@media only screen and (max-width: 600px) {img {width: 100%; margin: 0 auto; \/* Center the element *\/ }}"],"name":"LPT: Animal Capsule","settings":{"image":"shopify:\/\/shop_images\/JP_Home_Lifestyle_Page_LPT_2.png","full_width":true,"disable_top_spacing":true,"disable_bottom_spacing":false}},"multicolumn_FFwWx6":{"type":"multicolumn","blocks":{"column_Vz3Air":{"type":"column","name":"1","settings":{"image":"shopify:\/\/shop_images\/JP_Home_Lifestyle_Page-08.png","image_full_width":true,"image_link":"","retina":true,"title":"","text":"","link_label":"","link":""}},"column_GrCArW":{"type":"column","name":"2","settings":{"image":"shopify:\/\/shop_images\/JP_Home_Lifestyle_Page-09.png","image_full_width":true,"image_link":"","retina":true,"title":"","text":"","link_label":"","link":""}},"column_LcAcH4":{"type":"column","name":"3","settings":{"image":"shopify:\/\/shop_images\/JP_Home_Lifestyle_Page-10.png","image_full_width":true,"image_link":"","retina":true,"title":"","text":"","link_label":"","link":""}}},"block_order":["column_Vz3Air","column_GrCArW","column_LcAcH4"],"name":"3Block: Animal Capsule","settings":{"heading":"","heading_left":true,"description":"","full_width":false,"display_type":"grid","image_ratio":"adapt","columns_desktop":3,"text_alignment":"left","heading_size":"h5","mobile_swipe":true,"show_progress_bar":true,"disable_top_spacing":true,"disable_bottom_spacing":false}}},"order":["main","slideshow_hM9xbj","spacer_hckc3N","rich_text_X8RFyy","rich_text_7hmYrg","multicolumn_PKXkUq","spacer_4NyKKa","rich_text_i67AyK","collection_tabs_JyaJkc","spacer_CikTKW","rich_text_WDD3eK","single_image_N7FJj6","multicolumn_EzgfxQ","spacer_tbiAh6","rich_text_zPA9gg","single_image_QX9Htx","multicolumn_FFwWx6"]}